xrandroll/__init__.py
xrandroll/__main__.py
xrandroll/main.py
xrandroll/main.ui
xrandroll/monitor.py
xrandroll/monitor_item.py
xrandroll/xrandr.py
xrandroll-0.1.7.dist-info/entry_points.txt
xrandroll-0.1.7.dist-info/LICENSE
xrandroll-0.1.7.dist-info/WHEEL
xrandroll-0.1.7.dist-info/METADATA
xrandroll-0.1.7.dist-info/RECORD
