Metadata-Version: 2.1
Name: xrandroll
Version: 0.1.7
Summary: A powertool to configure your display
Home-page: https://github.com/ralsina/xrandroll
License: MIT
Author: Roberto Alsina
Author-email: roberto.alsina@gmail.com
Requires-Python: >=3.7,<3.11
Classifier: License :: OSI Approved :: MIT License
Classifier: Programming Language :: Python :: 3
Classifier: Programming Language :: Python :: 3.10
Classifier: Programming Language :: Python :: 3.7
Classifier: Programming Language :: Python :: 3.8
Classifier: Programming Language :: Python :: 3.9
Requires-Dist: parse (>1.0)
Requires-Dist: pyedid (>=0.1)
Requires-Dist: pyside2 (>5.14)
